{
  "data": [
    {
      "companyName": "JOHN SPRINZEL",
      "slug": "john-sprinzel",
      "link": "https://www.mk1-performance-conversions.co.uk/john_sprinzel.htm",
      "image": "https://www.mk1-performance-conversions.co.uk/wpimages/wp5098f09a_06.png"
    },
    {
      "companyName": "TAURUS",
      "slug": "taurus",
      "link": "https://www.mk1-performance-conversions.co.uk/taurus_history.htm",
      "image": "https://www.mk1-performance-conversions.co.uk/wpimages/wpdd0754e4_06.png"
    },
    {
      "companyName": "TILLING AUTOMOTIVE",
      "slug": "tilling-automotive",
      "link": "https://www.mk1-performance-conversions.co.uk/tilling-auto.htm",
      "image": "https://www.mk1-performance-conversions.co.uk/wpimages/wpd971a833_06.png"
    },
    {
      "companyName": "HAAN",
      "slug": "haan",
      "link": "https://www.mk1-performance-conversions.co.uk//vb_haan.html",
      "image": "https://www.mk1-performance-conversions.co.uk/wpimages/wpf2a73335_06.png"
    },
    {
      "companyName": "WOODING",
      "slug": "wooding",
      "link": "https://www.mk1-performance-conversions.co.uk/wooding.htm",
      "image": "https://www.mk1-performance-conversions.co.uk/wpimages/wp0ff0e727_06.png"
    },
    {
      "companyName": "WILHELM BUSCH",
      "slug": "wilhelm-busch",
      "link": "https://www.mk1-performance-conversions.co.uk/busch.htm",
      "image": "https://www.mk1-performance-conversions.co.uk/wpimages/wp6f7b8d2e_06.png"
    },
    {
      "companyName": "JURGEN WORTMAN",
      "slug": "jurgen-wortman",
      "link": "https://www.mk1-performance-conversions.co.uk/wortman.htm",
      "image": "https://www.mk1-performance-conversions.co.uk/wpimages/wp56834206_06.png"
    },
    {
      "companyName": "WOOD and PICKETT",
      "slug": "wood-and-pickett",
      "link": "https://www.mk1-performance-conversions.co.uk/wood-n-picket.htm",
      "image": "https://www.mk1-performance-conversions.co.uk/wpimages/wp9daf1d67_06.png"
    },
    {
      "companyName": "YAZAKI",
      "slug": "yazaki",
      "link": "https://www.mk1-performance-conversions.co.uk//yazaki.html",
      "image": "https://www.mk1-performance-conversions.co.uk/wpimages/wp9c078686_05_06.jpg"
    },
    {
      "companyName": "YIMKIN",
      "slug": "yimkin",
      "link": "https://www.mk1-performance-conversions.co.uk/yimkin.htm",
      "image": "https://www.mk1-performance-conversions.co.uk/wpimages/wp12a17660_06.png"
    },
    {
      "companyName": "JANSPEED",
      "slug": "janspeed",
      "link": "https://www.mk1-performance-conversions.co.uk/janspeed.htm",
      "image": "https://www.mk1-performance-conversions.co.uk/wpimages/wp94b3ec45_06.png"
    },
    {
      "companyName": "KAROBES",
      "slug": "karobes",
      "link": "http://mk1-performance-conversions.co.uk/karobes.htm",
      "image": "https://www.mk1-performance-conversions.co.uk/wpimages/wp3fd6d39c_06.png"
    },
    {
      "companyName": "RICHARD LONGMAN and CO",
      "slug": "richard-longman-and-co",
      "link": "http://mk1-performance-conversions.co.uk/longman.htm",
      "image": "https://www.mk1-performance-conversions.co.uk/wpimages/wpae27d091_06.png"
    },
    {
      "companyName": "LES LESTON ACCESSORIES",
      "slug": "les-leston-accessories",
      "link": "https://www.mk1-performance-conversions.co.uk/les_leston.htm",
      "image": "https://www.mk1-performance-conversions.co.uk/wpimages/wp290f53d3_06.png"
    },
    {
      "companyName": "RALLYE AUTO SPORT",
      "slug": "rallye-auto-sport",
      "link": "https://www.mk1-performance-conversions.co.uk/marnat.htm",
      "image": "https://www.mk1-performance-conversions.co.uk/wpimages/wp327d9b8e_06.png"
    },
    {
      "companyName": "MANGOLETSI",
      "slug": "mangoletsi",
      "link": "https://www.mk1-performance-conversions.co.uk/mangoletsi.htm",
      "image": "https://www.mk1-performance-conversions.co.uk/wpimages/wp4d59ff98_06.png"
    },
    {
      "companyName": "MINILITE",
      "slug": "minilite",
      "link": "https://www.mk1-performance-conversions.co.uk/minilite.htm",
      "image": "https://www.mk1-performance-conversions.co.uk/wpimages/wp14212d1a_06.png"
    },
    {
      "companyName": "DON MOORE",
      "slug": "don-moore",
      "link": "https://www.mk1-performance-conversions.co.uk/don_moore.htm",
      "image": "https://www.mk1-performance-conversions.co.uk/wpimages/wp341c57ad_06.png"
    },
    {
      "companyName": "MOTORPLUS",
      "slug": "motorplus",
      "link": "http://mk1-performance-conversions.co.uk/motorplus.htm",
      "image": "https://www.mk1-performance-conversions.co.uk/wpimages/wp90476c2f_06.png"
    },
    {
      "companyName": "MABMA DEVELOPMENTS",
      "slug": "mabma-developments",
      "link": "https://www.mk1-performance-conversions.co.uk/mamba.htm",
      "image": "https://www.mk1-performance-conversions.co.uk/wpimages/wp8a8eea7c_06.png"
    },
    {
      "companyName": "MOTO-LITA",
      "slug": "moto-lita",
      "link": "https://www.mk1-performance-conversions.co.uk/moto-lita.htm",
      "image": "https://www.mk1-performance-conversions.co.uk/wpimages/wp12861cd2_06.png"
    },
    {
      "companyName": "MOTORTUNE",
      "slug": "motortune",
      "link": "https://www.mk1-performance-conversions.co.uk/motortune.htm",
      "image": "https://www.mk1-performance-conversions.co.uk/wpimages/wp65247f9e_06.png"
    },
    {
      "companyName": "JV MURCOTT",
      "slug": "jv-murcott",
      "link": "https://www.mk1-performance-conversions.co.uk//murcott.html",
      "image": "https://www.mk1-performance-conversions.co.uk/wpimages/wp8d225bb3_06.jpg"
    },
    {
      "companyName": "NORDIC",
      "slug": "nordic",
      "link": "https://www.mk1-performance-conversions.co.uk/nordic.htm",
      "image": "https://www.mk1-performance-conversions.co.uk/wpimages/wp21544895_06.png"
    },
    {
      "companyName": "NERUS",
      "slug": "nerus",
      "link": "https://www.mk1-performance-conversions.co.uk/nerus.htm",
      "image": "https://www.mk1-performance-conversions.co.uk/wpimages/wp2f3d04ba_06.png"
    },
    {
      "companyName": "NETLAP PLANET ENGINEERING",
      "slug": "netlap-planet-engineering",
      "link": "https://www.mk1-performance-conversions.co.uk//netlap.html",
      "image": "https://www.mk1-performance-conversions.co.uk/wpimages/wp1172a8e1_06.png"
    },
    {
      "companyName": "OSELLI ENGINEERING",
      "slug": "oselli-engineering",
      "link": "https://www.mk1-performance-conversions.co.uk/oselli.htm",
      "image": "https://www.mk1-performance-conversions.co.uk/wpimages/wp5a17fbb9_06.png"
    },
    {
      "companyName": "PADDY HOPKIRK PRODUCTS",
      "slug": "paddy-hopkirk-products",
      "link": "https://www.mk1-performance-conversions.co.uk/paddy_hopkirk.htm",
      "image": "https://www.mk1-performance-conversions.co.uk/wpimages/wpba3c7524_06.png"
    },
    {
      "companyName": "JA PEARCE",
      "slug": "ja-pearce",
      "link": "https://www.mk1-performance-conversions.co.uk/ja-pearce.htm",
      "image": "https://www.mk1-performance-conversions.co.uk/wpimages/wp7c57e64c_06.png"
    },
    {
      "companyName": "PEARSON",
      "slug": "pearson",
      "link": "https://www.mk1-performance-conversions.co.uk/pearson.htm",
      "image": "https://www.mk1-performance-conversions.co.uk/wpimages/wp6dab85c7_06.png"
    },
    {
      "companyName": "PECO",
      "slug": "peco",
      "link": "https://www.mk1-performance-conversions.co.uk/peco.htm",
      "image": "https://www.mk1-performance-conversions.co.uk/wpimages/wp6f2c33ae_06.png"
    },
    {
      "companyName": "RALLYE-SHOP",
      "slug": "rallye-shop",
      "link": "https://www.mk1-performance-conversions.co.uk/rally-shop.htm",
      "image": "https://www.mk1-performance-conversions.co.uk/wpimages/wpacb2aa8b_06.png"
    },
    {
      "companyName": "ROTARY SPEED",
      "slug": "rotary-speed",
      "link": "https://www.mk1-performance-conversions.co.uk/rotary_speed.htm",
      "image": "https://www.mk1-performance-conversions.co.uk/wpimages/wpd1211e5b_06.png"
    },
    {
      "companyName": "RAYDYOT",
      "slug": "raydyot",
      "link": "https://www.mk1-performance-conversions.co.uk/raydyot.htm",
      "image": "https://www.mk1-performance-conversions.co.uk/wpimages/wp83678613_06.png"
    },
    {
      "companyName": "RESTALL BROS",
      "slug": "restall-bros",
      "link": "https://www.mk1-performance-conversions.co.uk/restall.htm",
      "image": "https://www.mk1-performance-conversions.co.uk/wpimages/wp38796ca4_06.png"
    },
    {
      "companyName": "REVOLUTION WHEELS",
      "slug": "revolution-wheels",
      "link": "https://www.mk1-performance-conversions.co.uk//revolution wheels.html",
      "image": "https://www.mk1-performance-conversions.co.uk/wpimages/wpdb86ae01_06.png"
    },
    {
      "companyName": "RJV",
      "slug": "rjv",
      "link": "http://mk1-performance-conversions.co.uk/rjv.html",
      "image": "https://www.mk1-performance-conversions.co.uk/wpimages/wp67636335_06.png"
    },
    {
      "companyName": "SHORROCK SUPERCHARGERS",
      "slug": "shorrock-superchargers",
      "link": "http://mk1-performance-conversions.co.uk/shorrock_intro.htm",
      "image": "https://www.mk1-performance-conversions.co.uk/wpimages/wp89ed835b_06.png"
    },
    {
      "companyName": "BOB SOPER LTD",
      "slug": "bob-soper-ltd",
      "link": "http://mk1-performance-conversions.co.uk/bob_soper.htm",
      "image": "https://www.mk1-performance-conversions.co.uk/wpimages/wp01b5d775_06.png"
    },
    {
      "companyName": "SPEEDWELL",
      "slug": "speedwell",
      "link": "http://mk1-performance-conversions.co.uk/spdhist.htm",
      "image": "https://www.mk1-performance-conversions.co.uk/wpimages/wpde283650_06.png"
    },
    {
      "companyName": "STYLA ACCESSORIES",
      "slug": "styla-accessories",
      "link": "https://www.mk1-performance-conversions.co.uk/styla.htm",
      "image": "https://www.mk1-performance-conversions.co.uk/wpimages/wp8aaebdd1_06.png"
    },
    {
      "companyName": "SUPER ACCESSORIES",
      "slug": "super-accessories",
      "link": "https://www.mk1-performance-conversions.co.uk/super_acc.htm",
      "image": "https://www.mk1-performance-conversions.co.uk/wpimages/wpe3d6cedb_06.png"
    },
    {
      "companyName": "SPEED CENTRE",
      "slug": "speed-centre",
      "link": "https://www.mk1-performance-conversions.co.uk//speed_centre.html",
      "image": "https://www.mk1-performance-conversions.co.uk/wpimages/wpe5a71475_05_06.jpg"
    },
    {
      "companyName": "SPQR",
      "slug": "spqr",
      "link": "https://www.mk1-performance-conversions.co.uk/spqr.htm",
      "image": "https://www.mk1-performance-conversions.co.uk/wpimages/wpf7de90b7_06.png"
    },
    {
      "companyName": "ALEXANDER ENGINEERING COMPANY",
      "slug": "alexander-engineering-company",
      "link": "http://mk1-performance-conversions.co.uk/alexander_eng.htm",
      "image": "https://www.mk1-performance-conversions.co.uk/wpimages/wpf0ae631d_06.png"
    },
    {
      "companyName": "JOHN ALEY RACING",
      "slug": "john-aley-racing",
      "link": "https://www.mk1-performance-conversions.co.uk/john_aley.htm",
      "image": "https://www.mk1-performance-conversions.co.uk/wpimages/wpe6570db5_06.png"
    },
    {
      "companyName": "AQUAPLANE CO Ltd",
      "slug": "aquaplane-co-ltd",
      "link": "https://www.mk1-performance-conversions.co.uk/aquaplane.htm",
      "image": "https://www.mk1-performance-conversions.co.uk/wpimages/wpb451e7de_06.png"
    },
    {
      "companyName": "ARDEN CONVERSIONS",
      "slug": "arden-conversions",
      "link": "https://www.mk1-performance-conversions.co.uk/arden_eng.htm",
      "image": "https://www.mk1-performance-conversions.co.uk/wpimages/wp71e5c5b3_06.png"
    },
    {
      "companyName": "ARDEN ACCESSORIES",
      "slug": "arden-accessories",
      "link": "https://www.mk1-performance-conversions.co.uk//arden_continental.html",
      "image": "https://www.mk1-performance-conversions.co.uk/wpimages/wpd5176275_06.png"
    },
    {
      "companyName": "JOHN RHODES AUTOSPEED",
      "slug": "john-rhodes-autospeed",
      "link": "https://www.mk1-performance-conversions.co.uk/autospeed.htm",
      "image": "https://www.mk1-performance-conversions.co.uk/wpimages/wpa672571b_06.png"
    },
    {
      "companyName": "BARNACLE ACCESSORIES",
      "slug": "barnacle-accessories",
      "link": "https://www.mk1-performance-conversions.co.uk//barnacle.html",
      "image": "https://www.mk1-performance-conversions.co.uk/wpimages/wp136d7214_06.png"
    },
    {
      "companyName": "BARWELL MOTORS",
      "slug": "barwell-motors",
      "link": "http://mk1-performance-conversions.co.uk/barwell.htm",
      "image": "https://www.mk1-performance-conversions.co.uk/wpimages/wp03ff4eb3_06.png"
    },
    {
      "companyName": "BLUEMEL BROS LTD",
      "slug": "bluemel-bros-ltd",
      "link": "http://mk1-performance-conversions.co.uk/bluemels.htm",
      "image": "https://www.mk1-performance-conversions.co.uk/wpimages/wpde99304e_06.png"
    },
    {
      "companyName": "BMC ST and COMPS DEPT",
      "slug": "bmc-st-and-comps-dept",
      "link": "http://mk1-performance-conversions.co.uk/special_tuning.htm",
      "image": "https://www.mk1-performance-conversions.co.uk/wpimages/wp6d653be8_06.png"
    },
    {
      "companyName": "Brabham",
      "slug": "brabham",
      "link": "http://mk1-performance-conversions.co.uk/brabham.htm",
      "image": "https://www.mk1-performance-conversions.co.uk/wpimages/wp445ee863_06.png"
    },
    {
      "companyName": "BRITISH VITA RACING and TUNING",
      "slug": "british-vita-racing-and-tuning",
      "link": "https://www.mk1-performance-conversions.co.uk//brt.html",
      "image": "https://www.mk1-performance-conversions.co.uk/wpimages/wp96425ea8_06.png"
    },
    {
      "companyName": "BROADSPEED",
      "slug": "broadspeed",
      "link": "http://mk1-performance-conversions.co.uk/broadspeed.htm",
      "image": "https://www.mk1-performance-conversions.co.uk/wpimages/wpc1eb0685_06.png"
    },
    {
      "companyName": "BROWN and GEESON",
      "slug": "brown-and-geeson",
      "link": "http://mk1-performance-conversions.co.uk/bg.htm",
      "image": "https://www.mk1-performance-conversions.co.uk/wpimages/wpd1d66a3b_06.png"
    },
    {
      "companyName": "BUTLERS",
      "slug": "butlers",
      "link": "http://mk1-performance-conversions.co.uk/butlers.htm",
      "image": "https://www.mk1-performance-conversions.co.uk/wpimages/wpa053de10_06.png"
    },
    {
      "companyName": "COBURN IMPROVEMENTS",
      "slug": "coburn-improvements",
      "link": "http://mk1-performance-conversions.co.uk/coburn.htm",
      "image": "https://www.mk1-performance-conversions.co.uk/wpimages/wp140cfd5a_06.png"
    },
    {
      "companyName": "COLDWELL ENGINEERING",
      "slug": "coldwell-engineering",
      "link": "http://mk1-performance-conversions.co.uk/coldwell_engineering.htm",
      "image": "https://www.mk1-performance-conversions.co.uk/wpimages/wp6901dfba_06.png"
    },
    {
      "companyName": "CONVERSION and TUNING",
      "slug": "conversion-and-tuning",
      "link": "http://mk1-performance-conversions.co.uk/conversion_tuning.htm",
      "image": "https://www.mk1-performance-conversions.co.uk/wpimages/wp9aaed61c_06.png"
    },
    {
      "companyName": "COOPER CAR COMPANY",
      "slug": "cooper-car-company",
      "link": "http://mk1-performance-conversions.co.uk/cooper_car_co.htm",
      "image": "https://www.mk1-performance-conversions.co.uk/wpimages/wpb5c2a45a_06.png"
    },
    {
      "companyName": "COSMIC ACCESSORIES",
      "slug": "cosmic-accessories",
      "link": "http://mk1-performance-conversions.co.uk/cosmic.htm",
      "image": "https://www.mk1-performance-conversions.co.uk/wpimages/wp8c68b46c_06.png"
    },
    {
      "companyName": "COX OF WATFORD",
      "slug": "cox-of-watford",
      "link": "https://www.mk1-performance-conversions.co.uk//cox_seats.html",
      "image": "https://www.mk1-performance-conversions.co.uk/wpimages/wpdd7e7ec4_06.png"
    },
    {
      "companyName": "CUD ACCESSORIES",
      "slug": "cud-accessories",
      "link": "https://www.mk1-performance-conversions.co.uk/page153.html",
      "image": "https://www.mk1-performance-conversions.co.uk/wpimages/wpa89eb8a8_06.jpg"
    },
    {
      "companyName": "NEAL DAVIS RACING",
      "slug": "neal-davis-racing",
      "link": "http://mk1-performance-conversions.co.uk/neal_davis.htm",
      "image": "https://www.mk1-performance-conversions.co.uk/wpimages/wpda0ac294_06.png"
    },
    {
      "companyName": "DOWNTON ENGINEERING WORKS",
      "slug": "downton-engineering-works",
      "link": "http://mk1-performance-conversions.co.uk/downton.htm",
      "image": "https://www.mk1-performance-conversions.co.uk/wpimages/wpfd76d001_06.png"
    },
    {
      "companyName": "DERRINGTON",
      "slug": "derrington",
      "link": "http://mk1-performance-conversions.co.uk/derrington.htm",
      "image": "https://www.mk1-performance-conversions.co.uk/wpimages/wpd8db76bb_06.png"
    },
    {
      "companyName": "PAUL EMERY",
      "slug": "paul-emery",
      "link": "https://www.mk1-performance-conversions.co.uk//p_emery.html",
      "image": "https://www.mk1-performance-conversions.co.uk/wpimages/wpac7105b3_06.jpg"
    },
    {
      "companyName": "FORSPEED",
      "slug": "forspeed",
      "link": "http://mk1-performance-conversions.co.uk/forspeed.htm",
      "image": "https://www.mk1-performance-conversions.co.uk/wpimages/wp044717f6_06.png"
    },
    {
      "companyName": "PADDY GASTON",
      "slug": "paddy-gaston",
      "link": "http://mk1-performance-conversions.co.uk/paddy_gaston.htm",
      "image": "https://www.mk1-performance-conversions.co.uk/wpimages/wpac2e33a1_06.png"
    },
    {
      "companyName": "GIRLING",
      "slug": "girling",
      "link": "https://www.mk1-performance-conversions.co.uk/girling.htm",
      "image": "https://www.mk1-performance-conversions.co.uk/wpimages/wpc7cb9368_06.png"
    },
    {
      "companyName": "GRAFER TUNE",
      "slug": "grafer-tune",
      "link": "https://www.mk1-performance-conversions.co.uk//grafer_tune.html",
      "image": "https://www.mk1-performance-conversions.co.uk/wpimages/wp87a05456_06.png"
    },
    {
      "companyName": "HALDA",
      "slug": "halda",
      "link": "https://www.mk1-performance-conversions.co.uk//halda.html",
      "image": "https://www.mk1-performance-conversions.co.uk/wpimages/wpa65df179_05_06.jpg"
    },
    {
      "companyName": "HARESPARES AUTORAMA",
      "slug": "harespares-autorama",
      "link": "http://mk1-performance-conversions.co.uk/harespares-autorama.htm",
      "image": "https://www.mk1-performance-conversions.co.uk/wpimages/wp794a7c5c_06.png"
    },
    {
      "companyName": "HI-LO",
      "slug": "hi-lo",
      "link": "http://mk1-performance-conversions.co.uk/hilo.htm",
      "image": "https://www.mk1-performance-conversions.co.uk/wpimages/wp544161f9_06.png"
    },
    {
      "companyName": "TERRY HUNTER LTD",
      "slug": "terry-hunter-ltd",
      "link": "https://www.mk1-performance-conversions.co.uk/hunter.htm",
      "image": "https://www.mk1-performance-conversions.co.uk/wpimages/wp9a523474_06.png"
    }
  ],
  "source": "https://www.mk1-performance-conversions.co.uk/mk1_the_tuning_archive.htm"
}
